heaven_test_package_herc01/__init__.py
heaven_test_package_herc01/calculator_v2.py
heaven_test_package_herc01/use_calculator_v2.py
heaven_test_package_herc01-0.1.1.dist-info/METADATA
heaven_test_package_herc01-0.1.1.dist-info/WHEEL
heaven_test_package_herc01-0.1.1.dist-info/top_level.txt
heaven_test_package_herc01-0.1.1.dist-info/RECORD
